dynamic_image/__init__.py
dynamic_image/fields.py
dynamic_image/mixins.py
dynamic_image/utils.py
dynamic_upload_image_field/__init__.py
dynamic_upload_image_field/fields.py
django_dynamic_image-1.4.0.dist-info/LICENSE.txt
django_dynamic_image-1.4.0.dist-info/METADATA
django_dynamic_image-1.4.0.dist-info/WHEEL
django_dynamic_image-1.4.0.dist-info/top_level.txt
django_dynamic_image-1.4.0.dist-info/RECORD
