Metadata-Version: 2.1
Name: django-dynamic-image
Version: 1.4.0
Summary: A django ImageField whose upload_to value is generated from a model method
Home-page: https://github.com/alexseitsinger/django-dynamic-image
Author: Alex Seitsinger
Author-email: software@alexseitsinger.com
License: BSD 2-Clause License
Project-URL: Documentation, https://github.com/alexseitsinger/django-dynamic-image
Project-URL: Source, https://github.com/alexseitsinger/django-dynamic-image
Project-URL: Tracker, https://github.com/alexseitsinger/django-dynamic-image/issues
Keywords: django,imagefield
Platform: UNKNOWN
Classifier: Development Status :: 5 - Production/Stable
Classifier: Environment :: Web Environment
Classifier: Framework :: Django
Classifier: Intended Audience :: Developers
Classifier: License :: OSI Approved :: BSD License
Classifier: Natural Language :: English
Classifier: Operating System :: OS Independent
Classifier: Programming Language :: Python :: 2
Classifier: Programming Language :: Python :: 3
Classifier: Topic :: Internet :: WWW/HTTP :: Dynamic Content :: Content Management System
Requires-Dist: Django
Requires-Dist: requests
Requires-Dist: image-tools
